pulpcore/__init__.py
pulpcore/client/__init__.py
pulpcore/client/pulpcore/__init__.py
pulpcore/client/pulpcore/api_client.py
pulpcore/client/pulpcore/api_response.py
pulpcore/client/pulpcore/configuration.py
pulpcore/client/pulpcore/exceptions.py
pulpcore/client/pulpcore/py.typed
pulpcore/client/pulpcore/rest.py
pulpcore/client/pulpcore/api/__init__.py
pulpcore/client/pulpcore/api/access_policies_api.py
pulpcore/client/pulpcore/api/artifacts_api.py
pulpcore/client/pulpcore/api/content_api.py
pulpcore/client/pulpcore/api/content_openpgp_publickey_api.py
pulpcore/client/pulpcore/api/content_openpgp_publicsubkey_api.py
pulpcore/client/pulpcore/api/content_openpgp_signature_api.py
pulpcore/client/pulpcore/api/content_openpgp_userattribute_api.py
pulpcore/client/pulpcore/api/content_openpgp_userid_api.py
pulpcore/client/pulpcore/api/contentguards_api.py
pulpcore/client/pulpcore/api/contentguards_composite_api.py
pulpcore/client/pulpcore/api/contentguards_content_redirect_api.py
pulpcore/client/pulpcore/api/contentguards_header_api.py
pulpcore/client/pulpcore/api/contentguards_rbac_api.py
pulpcore/client/pulpcore/api/distributions_api.py
pulpcore/client/pulpcore/api/distributions_artifacts_api.py
pulpcore/client/pulpcore/api/distributions_openpgp_api.py
pulpcore/client/pulpcore/api/domains_api.py
pulpcore/client/pulpcore/api/exporters_filesystem_api.py
pulpcore/client/pulpcore/api/exporters_filesystem_exports_api.py
pulpcore/client/pulpcore/api/exporters_pulp_api.py
pulpcore/client/pulpcore/api/exporters_pulp_exports_api.py
pulpcore/client/pulpcore/api/groups_api.py
pulpcore/client/pulpcore/api/groups_roles_api.py
pulpcore/client/pulpcore/api/groups_users_api.py
pulpcore/client/pulpcore/api/importers_pulp_api.py
pulpcore/client/pulpcore/api/importers_pulp_import_check_api.py
pulpcore/client/pulpcore/api/importers_pulp_imports_api.py
pulpcore/client/pulpcore/api/livez_api.py
pulpcore/client/pulpcore/api/login_api.py
pulpcore/client/pulpcore/api/orphans_api.py
crc_pulpcore_client-20251023.3.dist-info/METADATA
crc_pulpcore_client-20251023.3.dist-info/WHEEL
crc_pulpcore_client-20251023.3.dist-info/top_level.txt
crc_pulpcore_client-20251023.3.dist-info/RECORD
